python/src/lazylearn/__init__.py
python/src/lazylearn/lazylearn.py
python/src/lazylearn/errors/__init__.py
python/src/lazylearn/errors/errors.py
python/src/lazylearn/ingestion/__init__.py
python/src/lazylearn/ingestion/ingestion_pipeline.py
python/src/lazylearn/ingestion/ingestion_pipeline_steps/__init__.py
python/src/lazylearn/ingestion/ingestion_pipeline_steps/data_parser_step.py
python/src/lazylearn/ingestion/ingestion_pipeline_steps/interpreter_step.py
python/src/lazylearn/ingestion/ingestion_pipeline_steps/summary_stats_step.py
python/src/lazylearn/ingestion/utils/__init__.py
python/src/lazylearn/ingestion/utils/csv.py
python/src/lazylearn/model_selection/__init__.py
python/src/lazylearn/model_selection/splitters.py
python/src/lazylearn/models/__init__.py
python/src/lazylearn/models/models.py
python/src/lazylearn/pipeline/__init__.py
python/src/lazylearn/pipeline/pipeline.py
python/src/lazylearn/preprocessing/__init__.py
python/src/lazylearn/preprocessing/encoding/__init__.py
python/src/lazylearn/preprocessing/encoding/encoders.py
python/src/lazylearn/preprocessing/imputation/__init__.py
python/src/lazylearn/preprocessing/time/__init__.py
python/src/lazylearn/preprocessing/time/date_processor.py
python/src/lazylearn/preprocessing/time/duration.py
python/src/lazylearn/regression/__init__.py
python/src/lazylearn/regression/models/__init__.py
python/src/lazylearn/regression/models/randomforest/__init__.py
python/src/lazylearn/regression/models/randomforest/randomforest.py
python/src/lazylearn/regression/models/randomforest/random_forest_steps/__init__.py
python/src/lazylearn/regression/models/randomforest/random_forest_steps/regressor_step.py
python/src/lazylearn/regression/models/xgboost/__init__.py
python/src/lazylearn/regression/models/xgboost/xgb.py
python/src/lazylearn/regression/models/xgboost/xgb_regressor_steps/__init__.py
python/src/lazylearn/regression/models/xgboost/xgb_regressor_steps/hpo_step.py
lazylearn-0.0.4.dist-info/METADATA
lazylearn-0.0.4.dist-info/WHEEL
lazylearn-0.0.4.dist-info/licenses/LICENSE
lazylearn-0.0.4.dist-info/RECORD
