Metadata-Version: 2.1
Name: lazylearn
Version: 0.0.4
Summary: lazy-learn is a high-level Python interface for automated machine learning (AutoML) for the lazy data scientist. While there are many AutoML libraries available each typically solves a niche area of the overall ML pipeline without providing a covering and approachable end-to-end system. lazy-learn aims at providing the most approachable and fastest access to building baseline models.
Project-URL: Homepage, https://github.com/frederikhoengaard/lazy-learn
Author-email: "Frederik P. Høngaard" <mail@frederikhoengaard.com>
License-File: LICENSE
Classifier: License :: OSI Approved :: MIT License
Classifier: Operating System :: OS Independent
Classifier: Programming Language :: Python :: 3
Requires-Python: >=3.7
